README.rst
setup.cfg
setup.py
./__init__.py
./carrier.py
./carrier.xml
./party.py
./sale.py
./sale.xml
./shipment.py
./shipment.xml
./tryton.cfg
./tests/__init__.py
./tests/test_shipment.py
./tests/test_shipment_gen.py
./tests/test_views_depends.py
./view/carrier_form.xml
./view/sale_configuration_view_form.xml
./view/sale_view_form.xml
./view/shipment_view_form.xml
./view/shipping_dhl_de_config_wizard_view_form.xml
./view/wizard_test_connection_start_form.xml
fio_shipping_dhl_de.egg-info/PKG-INFO
fio_shipping_dhl_de.egg-info/SOURCES.txt
fio_shipping_dhl_de.egg-info/dependency_links.txt
fio_shipping_dhl_de.egg-info/entry_points.txt
fio_shipping_dhl_de.egg-info/not-zip-safe
fio_shipping_dhl_de.egg-info/requires.txt
fio_shipping_dhl_de.egg-info/top_level.txt